Metadata-Version: 2.1
Name: pelican-similar-articles-light
Version: 1.0.0
Summary: A Pelican plugin to provide a support of similar articles, allowing users to access a list of articles linked to each article by a similarity calculation on their tags.
Home-page: https://github.com/ysard/pelican-similar-articles-light
Author: Ysard
Author-email: ysard@users.noreply.github.com
License: UNKNOWN
Keywords: pelican
Platform: UNKNOWN
Classifier: Development Status :: 5 - Production/Stable
Classifier: Intended Audience :: Developers
Classifier: Intended Audience :: System Administrators
Classifier: Intended Audience :: End Users/Desktop
Classifier: Programming Language :: Python :: 3
Classifier: Programming Language :: Python :: 3.6
Classifier: Programming Language :: Python :: 3.7
Classifier: Programming Language :: Python :: 3.8
Classifier: Programming Language :: Python :: 3.9
Classifier: Programming Language :: Python :: 3.10
Classifier: License :: OSI Approved :: GNU Affero General Public License v3 or later (AGPLv3+)
Provides-Extra: dev
